session_manager/__init__.py
session_manager/session_manager.py
session_manager/browser/__init__.py
botslab-0.1.0.dist-info/METADATA
botslab-0.1.0.dist-info/WHEEL
botslab-0.1.0.dist-info/top_level.txt
botslab-0.1.0.dist-info/RECORD
