Metadata-Version: 2.4
Name: botslab
Version: 0.1.0
Summary: Botslab General Library
Home-page: https://github.com/rilckbotslab/session_manager
Author: rilckbotslab
Author-email: rilckbotslab <rilck.lima@botslab.com.br>
License: MIT
Project-URL: Homepage, https://github.com/rilckbotslab/session_manager
Platform: any
Classifier: Programming Language :: Python :: 3
Classifier: Operating System :: OS Independent
Requires-Python: >=3.7
Requires-Dist: redis==5.0.1
Requires-Dist: python-dotenv==1.0.1
Requires-Dist: hvac==1.2.1
Dynamic: author
Dynamic: home-page
Dynamic: platform
Dynamic: requires-python
